trusylo/__init__.py
trusylo/client.py
trusylo/decorators.py
trusylo/exceptions.py
trusylo/middleware.py
trusylo-1.0.3.dist-info/METADATA
trusylo-1.0.3.dist-info/WHEEL
trusylo-1.0.3.dist-info/top_level.txt
trusylo-1.0.3.dist-info/RECORD
